README.md
setup.cfg
setup.py
time_def/__init__.py
time_def/time_def_.py
time_def.egg-info/PKG-INFO
time_def.egg-info/SOURCES.txt
time_def.egg-info/dependency_links.txt
time_def.egg-info/not-zip-safe
time_def.egg-info/top_level.txt