Metadata-Version: 2.1
Name: time-def
Version: 0.4
Summary: Print how long the function has been running
Home-page: UNKNOWN
Author: Maxim Fedotov
Author-email: maxf39@mail.ru
License: UNKNOWN
Platform: UNKNOWN
